removed/VERSION
removed/__init__.py
solo_python-0.1.1.dist-info/LICENSE-APACHE
solo_python-0.1.1.dist-info/LICENSE-MIT
solo_python-0.1.1.dist-info/WHEEL
solo_python-0.1.1.dist-info/METADATA
solo_python-0.1.1.dist-info/RECORD
